cdncheck.cpython-39-x86_64-linux-gnu.h
cdncheck.cpython-39-x86_64-linux-gnu.so
cdncheck-1.0.0.34.dist-info/entry_points.txt
cdncheck-1.0.0.34.dist-info/RECORD
cdncheck-1.0.0.34.dist-info/METADATA
cdncheck-1.0.0.34.dist-info/WHEEL
cdncheck/__init__.py
cdncheck/cdncheck.py
cdncheck/tests/test_cdncheck.py
cdncheck/tests/__init__.py
