Metadata-Version: 2.1
Name: cdncheck
Version: 1.0.0.34
Summary: A Python wrapper for ProjectDiscovery's cdncheck (https://github.com/projectdiscovery/cdncheck)
Home-page: https://github.com/blacklanternsecurity/cdncheck-python
License: GPL-3.0
Author: TheTechromancer
Requires-Python: >=3.7,<4.0
Classifier: License :: OSI Approved :: GNU General Public License v3 (GPLv3)
Classifier: Programming Language :: Python :: 3
Classifier: Programming Language :: Python :: 3.7
Classifier: Programming Language :: Python :: 3.8
Classifier: Programming Language :: Python :: 3.9
Classifier: Programming Language :: Python :: 3.10
Classifier: Programming Language :: Python :: 3.11
Project-URL: Repository, https://github.com/blacklanternsecurity/cdncheck-python
